{"global":{"$30k-$50k":2819,"$50k-$100k":5049,"$100k-$200k":3559,"$200k+":380,"$10k-$30k":2463,"I work for free :(":837,"$0-$10k":1148},"JPN":{"I work for free :(":1,"$0-$10k":0,"$10k-$30k":4,"$30k-$50k":17,"$50k-$100k":22,"$100k-$200k":4,"$200k+":2},"USA":{"I work for free :(":177,"$0-$10k":44,"$10k-$30k":67,"$30k-$50k":131,"$50k-$100k":1552,"$100k-$200k":2480,"$200k+":290},"AUS":{"I work for free :(":18,"$0-$10k":1,"$10k-$30k":6,"$30k-$50k":33,"$50k-$100k":215,"$100k-$200k":184,"$200k+":12},"IDN":{"I work for free :(":19,"$0-$10k":53,"$10k-$30k":19,"$30k-$50k":7,"$50k-$100k":2,"$100k-$200k":3,"$200k+":1},"CAN":{"I work for free :(":29,"$0-$10k":9,"$10k-$30k":17,"$30k-$50k":92,"$50k-$100k":428,"$100k-$200k":182,"$200k+":6},"FRA":{"I work for free :(":42,"$0-$10k":15,"$10k-$30k":98,"$30k-$50k":340,"$50k-$100k":256,"$100k-$200k":26,"$200k+":3},"IND":{"I work for free :(":52,"$0-$10k":96,"$10k-$30k":126,"$30k-$50k":66,"$50k-$100k":53,"$100k-$200k":14,"$200k+":5},"CHN":{"I work for free :(":5,"$0-$10k":7,"$10k-$30k":10,"$30k-$50k":18,"$50k-$100k":10,"$100k-$200k":2,"$200k+":0},"PHL":{"I work for free :(":6,"$0-$10k":34,"$10k-$30k":24,"$30k-$50k":6,"$50k-$100k":2,"$100k-$200k":0,"$200k+":0},"DEU":{"I work for free :(":57,"$0-$10k":38,"$10k-$30k":72,"$30k-$50k":189,"$50k-$100k":485,"$100k-$200k":86,"$200k+":4},"COL":{"I work for free :(":5,"$0-$10k":31,"$10k-$30k":41,"$30k-$50k":19,"$50k-$100k":8,"$100k-$200k":4,"$200k+":0},"PRT":{"I work for free :(":4,"$0-$10k":10,"$10k-$30k":62,"$30k-$50k":26,"$50k-$100k":14,"$100k-$200k":0,"$200k+":0},"HRV":{"I work for free :(":0,"$0-$10k":5,"$10k-$30k":20,"$30k-$50k":9,"$50k-$100k":7,"$100k-$200k":1,"$200k+":0},"GBR":{"I work for free :(":24,"$0-$10k":9,"$10k-$30k":45,"$30k-$50k":175,"$50k-$100k":318,"$100k-$200k":131,"$200k+":10},"POL":{"I work for free :(":20,"$0-$10k":30,"$10k-$30k":155,"$30k-$50k":150,"$50k-$100k":64,"$100k-$200k":13,"$200k+":2},"CZE":{"I work for free :(":6,"$0-$10k":6,"$10k-$30k":68,"$30k-$50k":71,"$50k-$100k":25,"$100k-$200k":10,"$200k+":2},"SVK":{"I work for free :(":2,"$0-$10k":4,"$10k-$30k":14,"$30k-$50k":11,"$50k-$100k":8,"$100k-$200k":0,"$200k+":1},"TUR":{"I work for free :(":10,"$0-$10k":22,"$10k-$30k":19,"$30k-$50k":6,"$50k-$100k":8,"$100k-$200k":3,"$200k+":0},"NLD":{"I work for free :(":16,"$0-$10k":9,"$10k-$30k":53,"$30k-$50k":129,"$50k-$100k":190,"$100k-$200k":40,"$200k+":4},"SWE":{"I work for free :(":24,"$0-$10k":2,"$10k-$30k":15,"$30k-$50k":167,"$50k-$100k":228,"$100k-$200k":25,"$200k+":2},"FIN":{"I work for free :(":5,"$0-$10k":4,"$10k-$30k":9,"$30k-$50k":47,"$50k-$100k":77,"$100k-$200k":11,"$200k+":0},"ARE":{"I work for free :(":0,"$0-$10k":0,"$10k-$30k":1,"$30k-$50k":0,"$50k-$100k":0,"$100k-$200k":3,"$200k+":3},"NOR":{"I work for free :(":3,"$0-$10k":1,"$10k-$30k":5,"$30k-$50k":13,"$50k-$100k":101,"$100k-$200k":41,"$200k+":1},"MYS":{"I work for free :(":3,"$0-$10k":6,"$10k-$30k":16,"$30k-$50k":9,"$50k-$100k":4,"$100k-$200k":1,"$200k+":0},"MUS":{"I work for free :(":1,"$0-$10k":0,"$10k-$30k":1,"$30k-$50k":1,"$50k-$100k":0,"$100k-$200k":0,"$200k+":0},"SGP":{"I work for free :(":3,"$0-$10k":1,"$10k-$30k":6,"$30k-$50k":18,"$50k-$100k":22,"$100k-$200k":5,"$200k+":3},"KOR":{"I work for free :(":3,"$0-$10k":1,"$10k-$30k":12,"$30k-$50k":11,"$50k-$100k":6,"$100k-$200k":3,"$200k+":0},"ZAF":{"I work for free :(":10,"$0-$10k":8,"$10k-$30k":28,"$30k-$50k":43,"$50k-$100k":40,"$100k-$200k":11,"$200k+":1},"ESP":{"I work for free :(":11,"$0-$10k":10,"$10k-$30k":76,"$30k-$50k":158,"$50k-$100k":72,"$100k-$200k":14,"$200k+":1},"EGY":{"I work for free :(":3,"$0-$10k":20,"$10k-$30k":10,"$30k-$50k":2,"$50k-$100k":3,"$100k-$200k":1,"$200k+":0},"NZL":{"I work for free :(":4,"$0-$10k":3,"$10k-$30k":2,"$30k-$50k":21,"$50k-$100k":65,"$100k-$200k":26,"$200k+":1},"THA":{"I work for free :(":4,"$0-$10k":4,"$10k-$30k":8,"$30k-$50k":4,"$50k-$100k":4,"$100k-$200k":0,"$200k+":0},"ARG":{"I work for free :(":9,"$0-$10k":36,"$10k-$30k":58,"$30k-$50k":25,"$50k-$100k":21,"$100k-$200k":7,"$200k+":0},"ISR":{"I work for free :(":11,"$0-$10k":4,"$10k-$30k":5,"$30k-$50k":17,"$50k-$100k":42,"$100k-$200k":30,"$200k+":3},"UKR":{"I work for free :(":12,"$0-$10k":60,"$10k-$30k":106,"$30k-$50k":78,"$50k-$100k":40,"$100k-$200k":5,"$200k+":0},"MKD":{"I work for free :(":1,"$0-$10k":0,"$10k-$30k":8,"$30k-$50k":2,"$50k-$100k":1,"$100k-$200k":0,"$200k+":0},"BGR":{"I work for free :(":4,"$0-$10k":2,"$10k-$30k":28,"$30k-$50k":23,"$50k-$100k":11,"$100k-$200k":2,"$200k+":1},"SRB":{"I work for free :(":2,"$0-$10k":17,"$10k-$30k":25,"$30k-$50k":18,"$50k-$100k":3,"$100k-$200k":3,"$200k+":0},"CHE":{"I work for free :(":13,"$0-$10k":4,"$10k-$30k":4,"$30k-$50k":6,"$50k-$100k":67,"$100k-$200k":53,"$200k+":5},"RUS":{"I work for free :(":41,"$0-$10k":136,"$10k-$30k":299,"$30k-$50k":115,"$50k-$100k":48,"$100k-$200k":8,"$200k+":2},"LBN":{"I work for free :(":0,"$0-$10k":0,"$10k-$30k":2,"$30k-$50k":1,"$50k-$100k":4,"$100k-$200k":1,"$200k+":0},"NPL":{"I work for free :(":1,"$0-$10k":9,"$10k-$30k":5,"$30k-$50k":0,"$50k-$100k":0,"$100k-$200k":0,"$200k+":0},"BRA":{"I work for free :(":27,"$0-$10k":92,"$10k-$30k":177,"$30k-$50k":62,"$50k-$100k":56,"$100k-$200k":9,"$200k+":1},"SVN":{"I work for free :(":4,"$0-$10k":1,"$10k-$30k":6,"$30k-$50k":11,"$50k-$100k":4,"$100k-$200k":0,"$200k+":0},"BLR":{"I work for free :(":8,"$0-$10k":18,"$10k-$30k":39,"$30k-$50k":23,"$50k-$100k":10,"$100k-$200k":1,"$200k+":0},"AUT":{"I work for free :(":7,"$0-$10k":5,"$10k-$30k":12,"$30k-$50k":37,"$50k-$100k":49,"$100k-$200k":9,"$200k+":1},"IRL":{"I work for free :(":1,"$0-$10k":0,"$10k-$30k":3,"$30k-$50k":20,"$50k-$100k":58,"$100k-$200k":18,"$200k+":0},"MEX":{"I work for free :(":8,"$0-$10k":25,"$10k-$30k":67,"$30k-$50k":30,"$50k-$100k":23,"$100k-$200k":2,"$200k+":1},"URY":{"I work for free :(":0,"$0-$10k":4,"$10k-$30k":11,"$30k-$50k":10,"$50k-$100k":9,"$100k-$200k":0,"$200k+":0},"ROU":{"I work for free :(":8,"$0-$10k":12,"$10k-$30k":66,"$30k-$50k":24,"$50k-$100k":12,"$100k-$200k":3,"$200k+":2},"GRC":{"I work for free :(":1,"$0-$10k":7,"$10k-$30k":31,"$30k-$50k":17,"$50k-$100k":12,"$100k-$200k":1,"$200k+":1},"ITA":{"I work for free :(":13,"$0-$10k":14,"$10k-$30k":72,"$30k-$50k":91,"$50k-$100k":38,"$100k-$200k":4,"$200k+":1},"HUN":{"I work for free :(":5,"$0-$10k":9,"$10k-$30k":41,"$30k-$50k":13,"$50k-$100k":9,"$100k-$200k":3,"$200k+":2},"BEL":{"I work for free :(":4,"$0-$10k":5,"$10k-$30k":51,"$30k-$50k":69,"$50k-$100k":38,"$100k-$200k":14,"$200k+":0},"CHL":{"I work for free :(":3,"$0-$10k":5,"$10k-$30k":10,"$30k-$50k":13,"$50k-$100k":8,"$100k-$200k":0,"$200k+":2},"BGD":{"I work for free :(":4,"$0-$10k":9,"$10k-$30k":5,"$30k-$50k":2,"$50k-$100k":0,"$100k-$200k":0,"$200k+":0},"KEN":{"I work for free :(":3,"$0-$10k":7,"$10k-$30k":3,"$30k-$50k":1,"$50k-$100k":1,"$100k-$200k":0,"$200k+":0},"NGA":{"I work for free :(":8,"$0-$10k":29,"$10k-$30k":9,"$30k-$50k":2,"$50k-$100k":1,"$100k-$200k":0,"$200k+":0},"DNK":{"I work for free :(":8,"$0-$10k":5,"$10k-$30k":7,"$30k-$50k":12,"$50k-$100k":98,"$100k-$200k":41,"$200k+":2},"NIC":{"I work for free :(":0,"$0-$10k":2,"$10k-$30k":2,"$30k-$50k":0,"$50k-$100k":0,"$100k-$200k":0,"$200k+":0},"PER":{"I work for free :(":5,"$0-$10k":6,"$10k-$30k":10,"$30k-$50k":4,"$50k-$100k":2,"$100k-$200k":0,"$200k+":0},"VNM":{"I work for free :(":0,"$0-$10k":9,"$10k-$30k":11,"$30k-$50k":2,"$50k-$100k":1,"$100k-$200k":0,"$200k+":0},"IRN":{"I work for free :(":5,"$0-$10k":12,"$10k-$30k":10,"$30k-$50k":2,"$50k-$100k":7,"$100k-$200k":0,"$200k+":0},"ECU":{"I work for free :(":1,"$0-$10k":4,"$10k-$30k":6,"$30k-$50k":2,"$50k-$100k":0,"$100k-$200k":0,"$200k+":0},"EST":{"I work for free :(":3,"$0-$10k":3,"$10k-$30k":17,"$30k-$50k":19,"$50k-$100k":6,"$100k-$200k":0,"$200k+":0},"BIH":{"I work for free :(":1,"$0-$10k":2,"$10k-$30k":5,"$30k-$50k":2,"$50k-$100k":2,"$100k-$200k":0,"$200k+":0},"MAR":{"I work for free :(":2,"$0-$10k":3,"$10k-$30k":7,"$30k-$50k":0,"$50k-$100k":1,"$100k-$200k":0,"$200k+":0},"VEN":{"I work for free :(":6,"$0-$10k":17,"$10k-$30k":1,"$30k-$50k":1,"$50k-$100k":0,"$100k-$200k":0,"$200k+":0},"PAK":{"I work for free :(":4,"$0-$10k":12,"$10k-$30k":8,"$30k-$50k":1,"$50k-$100k":4,"$100k-$200k":0,"$200k+":0},"LVA":{"I work for free :(":5,"$0-$10k":1,"$10k-$30k":7,"$30k-$50k":3,"$50k-$100k":10,"$100k-$200k":2,"$200k+":0},"MDA":{"I work for free :(":1,"$0-$10k":6,"$10k-$30k":16,"$30k-$50k":2,"$50k-$100k":1,"$100k-$200k":0,"$200k+":0},"LTU":{"I work for free :(":2,"$0-$10k":5,"$10k-$30k":14,"$30k-$50k":8,"$50k-$100k":5,"$100k-$200k":0,"$200k+":0},"TUN":{"I work for free :(":1,"$0-$10k":5,"$10k-$30k":2,"$30k-$50k":0,"$50k-$100k":0,"$100k-$200k":0,"$200k+":0},"TWN":{"I work for free :(":7,"$0-$10k":4,"$10k-$30k":17,"$30k-$50k":12,"$50k-$100k":0,"$100k-$200k":1,"$200k+":0},"DOM":{"I work for free :(":0,"$0-$10k":2,"$10k-$30k":6,"$30k-$50k":2,"$50k-$100k":1,"$100k-$200k":1,"$200k+":0},"CRI":{"I work for free :(":2,"$0-$10k":1,"$10k-$30k":4,"$30k-$50k":10,"$50k-$100k":7,"$100k-$200k":1,"$200k+":0},"PAN":{"I work for free :(":0,"$0-$10k":0,"$10k-$30k":4,"$30k-$50k":2,"$50k-$100k":0,"$100k-$200k":0,"$200k+":0},"BOL":{"I work for free :(":3,"$0-$10k":4,"$10k-$30k":9,"$30k-$50k":0,"$50k-$100k":1,"$100k-$200k":0,"$200k+":1},"KAZ":{"I work for free :(":2,"$0-$10k":3,"$10k-$30k":3,"$30k-$50k":0,"$50k-$100k":1,"$100k-$200k":0,"$200k+":0},"AZE":{"I work for free :(":0,"$0-$10k":2,"$10k-$30k":0,"$30k-$50k":0,"$50k-$100k":0,"$100k-$200k":0,"$200k+":0},"GHA":{"I work for free :(":1,"$0-$10k":7,"$10k-$30k":1,"$30k-$50k":1,"$50k-$100k":0,"$100k-$200k":0,"$200k+":0},"GTM":{"I work for free :(":0,"$0-$10k":1,"$10k-$30k":3,"$30k-$50k":0,"$50k-$100k":1,"$100k-$200k":0,"$200k+":0},"ISL":{"I work for free :(":0,"$0-$10k":0,"$10k-$30k":0,"$30k-$50k":0,"$50k-$100k":10,"$100k-$200k":4,"$200k+":0},"GEO":{"I work for free :(":1,"$0-$10k":1,"$10k-$30k":0,"$30k-$50k":1,"$50k-$100k":1,"$100k-$200k":0,"$200k+":0},"ARM":{"I work for free :(":1,"$0-$10k":2,"$10k-$30k":3,"$30k-$50k":0,"$50k-$100k":0,"$100k-$200k":0,"$200k+":0},"MLT":{"I work for free :(":1,"$0-$10k":0,"$10k-$30k":1,"$30k-$50k":9,"$50k-$100k":4,"$100k-$200k":0,"$200k+":0},"HKG":{"I work for free :(":1,"$0-$10k":3,"$10k-$30k":3,"$30k-$50k":7,"$50k-$100k":8,"$100k-$200k":2,"$200k+":0},"SLV":{"I work for free :(":1,"$0-$10k":2,"$10k-$30k":2,"$30k-$50k":2,"$50k-$100k":0,"$100k-$200k":0,"$200k+":0},"LUX":{"I work for free :(":0,"$0-$10k":0,"$10k-$30k":0,"$30k-$50k":4,"$50k-$100k":6,"$100k-$200k":0,"$200k+":0},"HND":{"I work for free :(":0,"$0-$10k":1,"$10k-$30k":4,"$30k-$50k":1,"$50k-$100k":0,"$100k-$200k":0,"$200k+":0},"ETH":{"I work for free :(":1,"$0-$10k":1,"$10k-$30k":0,"$30k-$50k":1,"$50k-$100k":1,"$100k-$200k":0,"$200k+":0},"PRI":{"I work for free :(":0,"$0-$10k":0,"$10k-$30k":1,"$30k-$50k":2,"$50k-$100k":2,"$100k-$200k":1,"$200k+":0},"CMR":{"I work for free :(":2,"$0-$10k":2,"$10k-$30k":0,"$30k-$50k":0,"$50k-$100k":1,"$100k-$200k":0,"$200k+":0},"ALB":{"I work for free :(":0,"$0-$10k":0,"$10k-$30k":1,"$30k-$50k":0,"$50k-$100k":0,"$100k-$200k":1,"$200k+":0},"MDG":{"I work for free :(":0,"$0-$10k":0,"$10k-$30k":0,"$30k-$50k":1,"$50k-$100k":0,"$100k-$200k":0,"$200k+":0},"NCL":{"I work for free :(":0,"$0-$10k":0,"$10k-$30k":0,"$30k-$50k":0,"$50k-$100k":1,"$100k-$200k":0,"$200k+":0},"CYP":{"I work for free :(":0,"$0-$10k":0,"$10k-$30k":2,"$30k-$50k":0,"$50k-$100k":3,"$100k-$200k":1,"$200k+":0},"DZA":{"I work for free :(":1,"$0-$10k":2,"$10k-$30k":0,"$30k-$50k":0,"$50k-$100k":1,"$100k-$200k":0,"$200k+":0},"BHS":{"I work for free :(":1,"$0-$10k":0,"$10k-$30k":0,"$30k-$50k":0,"$50k-$100k":0,"$100k-$200k":0,"$200k+":0},"NAM":{"I work for free :(":0,"$0-$10k":0,"$10k-$30k":0,"$30k-$50k":0,"$50k-$100k":0,"$100k-$200k":1,"$200k+":0},"MMR":{"I work for free :(":0,"$0-$10k":0,"$10k-$30k":1,"$30k-$50k":0,"$50k-$100k":0,"$100k-$200k":0,"$200k+":0},"ZMB":{"I work for free :(":0,"$0-$10k":5,"$10k-$30k":1,"$30k-$50k":0,"$50k-$100k":0,"$100k-$200k":0,"$200k+":0},"KWT":{"I work for free :(":0,"$0-$10k":0,"$10k-$30k":0,"$30k-$50k":0,"$50k-$100k":1,"$100k-$200k":0,"$200k+":0},"PRY":{"I work for free :(":0,"$0-$10k":3,"$10k-$30k":3,"$30k-$50k":1,"$50k-$100k":0,"$100k-$200k":1,"$200k+":0},"HTI":{"I work for free :(":0,"$0-$10k":2,"$10k-$30k":0,"$30k-$50k":0,"$50k-$100k":0,"$100k-$200k":0,"$200k+":0},"GGY":{"I work for free :(":0,"$0-$10k":0,"$10k-$30k":0,"$30k-$50k":0,"$50k-$100k":2,"$100k-$200k":0,"$200k+":0},"FRO":{"I work for free :(":0,"$0-$10k":0,"$10k-$30k":1,"$30k-$50k":0,"$50k-$100k":0,"$100k-$200k":0,"$200k+":0},"BLZ":{"I work for free :(":0,"$0-$10k":0,"$10k-$30k":1,"$30k-$50k":0,"$50k-$100k":0,"$100k-$200k":0,"$200k+":0},"IRQ":{"I work for free :(":0,"$0-$10k":0,"$10k-$30k":1,"$30k-$50k":0,"$50k-$100k":0,"$100k-$200k":1,"$200k+":0},"LKA":{"I work for free :(":0,"$0-$10k":1,"$10k-$30k":2,"$30k-$50k":0,"$50k-$100k":1,"$100k-$200k":0,"$200k+":0},"AGO":{"I work for free :(":0,"$0-$10k":0,"$10k-$30k":0,"$30k-$50k":1,"$50k-$100k":0,"$100k-$200k":0,"$200k+":0},"MNG":{"I work for free :(":0,"$0-$10k":1,"$10k-$30k":0,"$30k-$50k":0,"$50k-$100k":0,"$100k-$200k":0,"$200k+":0},"CUB":{"I work for free :(":0,"$0-$10k":2,"$10k-$30k":0,"$30k-$50k":0,"$50k-$100k":1,"$100k-$200k":0,"$200k+":0},"SAU":{"I work for free :(":1,"$0-$10k":0,"$10k-$30k":0,"$30k-$50k":0,"$50k-$100k":1,"$100k-$200k":1,"$200k+":0},"KHM":{"I work for free :(":0,"$0-$10k":2,"$10k-$30k":0,"$30k-$50k":0,"$50k-$100k":1,"$100k-$200k":0,"$200k+":0},"ZWE":{"I work for free :(":0,"$0-$10k":1,"$10k-$30k":1,"$30k-$50k":1,"$50k-$100k":0,"$100k-$200k":0,"$200k+":1},"UGA":{"I work for free :(":0,"$0-$10k":2,"$10k-$30k":0,"$30k-$50k":0,"$50k-$100k":0,"$100k-$200k":0,"$200k+":0},"SMR":{"I work for free :(":0,"$0-$10k":0,"$10k-$30k":1,"$30k-$50k":0,"$50k-$100k":0,"$100k-$200k":0,"$200k+":0},"SDN":{"I work for free :(":0,"$0-$10k":1,"$10k-$30k":0,"$30k-$50k":1,"$50k-$100k":0,"$100k-$200k":0,"$200k+":0},"KGZ":{"I work for free :(":0,"$0-$10k":2,"$10k-$30k":1,"$30k-$50k":0,"$50k-$100k":0,"$100k-$200k":0,"$200k+":0},"UZB":{"I work for free :(":0,"$0-$10k":2,"$10k-$30k":2,"$30k-$50k":0,"$50k-$100k":0,"$100k-$200k":0,"$200k+":0},"MNE":{"I work for free :(":0,"$0-$10k":0,"$10k-$30k":1,"$30k-$50k":1,"$50k-$100k":0,"$100k-$200k":0,"$200k+":0},"JOR":{"I work for free :(":2,"$0-$10k":0,"$10k-$30k":2,"$30k-$50k":0,"$50k-$100k":1,"$100k-$200k":0,"$200k+":0},"JAM":{"I work for free :(":0,"$0-$10k":0,"$10k-$30k":1,"$30k-$50k":0,"$50k-$100k":0,"$100k-$200k":0,"$200k+":0},"LIE":{"I work for free :(":0,"$0-$10k":0,"$10k-$30k":0,"$30k-$50k":0,"$50k-$100k":0,"$100k-$200k":1,"$200k+":0},"GIB":{"I work for free :(":0,"$0-$10k":0,"$10k-$30k":0,"$30k-$50k":0,"$50k-$100k":1,"$100k-$200k":0,"$200k+":0},"GLP":{"I work for free :(":0,"$0-$10k":0,"$10k-$30k":1,"$30k-$50k":0,"$50k-$100k":0,"$100k-$200k":0,"$200k+":0},"SEN":{"I work for free :(":0,"$0-$10k":0,"$10k-$30k":0,"$30k-$50k":1,"$50k-$100k":0,"$100k-$200k":0,"$200k+":0},"CYM":{"I work for free :(":0,"$0-$10k":0,"$10k-$30k":0,"$30k-$50k":0,"$50k-$100k":0,"$100k-$200k":2,"$200k+":0},"JEY":{"I work for free :(":0,"$0-$10k":0,"$10k-$30k":1,"$30k-$50k":0,"$50k-$100k":0,"$100k-$200k":0,"$200k+":0},"BRB":{"I work for free :(":0,"$0-$10k":0,"$10k-$30k":3,"$30k-$50k":1,"$50k-$100k":0,"$100k-$200k":0,"$200k+":0},"MOZ":{"I work for free :(":0,"$0-$10k":1,"$10k-$30k":0,"$30k-$50k":0,"$50k-$100k":0,"$100k-$200k":0,"$200k+":0}}